{
  "year": 2024,
  "partner_code": 84,
  "partner_name": "伯利兹",
  "total_export_value_usd": 661555.0,
  "total_export_value_cny": 4711382.35,
  "hs4_products": [
    {
      "hs4": "0703",
      "name_cn": "洋葱、青葱、大蒜及其他葱属蔬菜",
      "name_en": "0703 - Onions, shallots, garlic, leeks and other alliaceous vegetables; fresh or chilled",
      "export_value_usd": 263149.0,
      "export_value_cny": 1874062.71,
      "share_pct": 39.8,
      "hs2": "07"
    },
    {
      "hs4": "2106",
      "name_cn": "其他食品调制品",
      "name_en": "2106 - Food preparations not elsewhere specified or included",
      "export_value_usd": 165748.0,
      "export_value_cny": 1180404.05,
      "share_pct": 25.1,
      "hs2": "21"
    },
    {
      "hs4": "1604",
      "name_cn": "调制或保藏鱼；鱼子酱",
      "name_en": "1604 - Prepared or preserved fish; caviar and caviar substitutes prepared from fish eggs",
      "export_value_usd": 63526.0,
      "export_value_cny": 452411.78,
      "share_pct": 9.6,
      "hs2": "16"
    },
    {
      "hs4": "2008",
      "name_cn": "其他调制或保藏水果、坚果及植物食用部分",
      "name_en": "2008 - Fruit, nuts and other edible parts of plants; prepared or preserved in ways n.e.c., whether or not containing added sugar or other sweetening matter or spirit, not elsewhere specified or included",
      "export_value_usd": 54088.0,
      "export_value_cny": 385197.37,
      "share_pct": 8.2,
      "hs2": "20"
    },
    {
      "hs4": "2104",
      "name_cn": "汤料、肉汤及其制品",
      "name_en": "2104 - Soups and broths and preparations therefor; homogenised composite food preparations",
      "export_value_usd": 50200.0,
      "export_value_cny": 357508.29,
      "share_pct": 7.6,
      "hs2": "21"
    },
    {
      "hs4": "2005",
      "name_cn": "其他调制或保藏蔬菜",
      "name_en": "2005 - Vegetables preparations n.e.c.; prepared or preserved otherwise than by vinegar or acetic acid, not frozen, other than products of heading no. 2006",
      "export_value_usd": 47610.0,
      "export_value_cny": 339063.14,
      "share_pct": 7.2,
      "hs2": "20"
    },
    {
      "hs4": "0712",
      "name_cn": "干制蔬菜",
      "name_en": "0712 - Vegetables, dried; whole, cut, sliced, broken or in powder, but not further prepared",
      "export_value_usd": 12323.0,
      "export_value_cny": 87760.45,
      "share_pct": 1.9,
      "hs2": "07"
    },
    {
      "hs4": "2103",
      "name_cn": "调味汁、调味品及芥子粉",
      "name_en": "2103 - Sauces and preparations therefor; mixed condiments and mixed seasonings, mustard flour and meal and prepared mustard",
      "export_value_usd": 3998.0,
      "export_value_cny": 28472.47,
      "share_pct": 0.6,
      "hs2": "21"
    },
    {
      "hs4": "2007",
      "name_cn": "果酱、果冻、果泥及果糊",
      "name_en": "2007 - Jams, fruit jellies, marmalades, fruit or nut puree and fruit or nut pastes, being cooked preparations; whether or not containing added sugar or other sweetening matter",
      "export_value_usd": 913.0,
      "export_value_cny": 6502.09,
      "share_pct": 0.1,
      "hs2": "20"
    }
  ]
}